aitestgen/__init__.py
aitestgen/__main__.py
aitestgen/aitestgen.py
aitestgen/autotest.py
aitestgen/examples.py
aitestgen/types/function_data.py
aitestgen-0.0.2.dist-info/METADATA
aitestgen-0.0.2.dist-info/WHEEL
aitestgen-0.0.2.dist-info/entry_points.txt
aitestgen-0.0.2.dist-info/RECORD
