Metadata-Version: 2.1
Name: aitestgen
Version: 0.0.2
Summary: Tool to generate simple unit test using openai api
Author: Pablo España
Author-email: espana.pablo95@gmail.com
Requires-Python: >=3.11,<4.0
Classifier: Programming Language :: Python :: 3
Classifier: Programming Language :: Python :: 3.11
Classifier: Programming Language :: Python :: 3.12
Requires-Dist: click (>=8.1.7,<9.0.0)
Requires-Dist: openai (>=1.3.5,<2.0.0)
Requires-Dist: python-dotenv (>=1.0.0,<2.0.0)
